{"health_percentage":75,"description":"Linguagem de programação 100% em português baseada em TypeScript, independente de sistema operacional e dispositivo, e suporte a múltiplos dialetos.","documentation":"https://designliquido.github.io/delegua/","files":{"code_of_conduct":null,"code_of_conduct_file":null,"contributing":{"url":"https://api.github.com/repos/DesignLiquido/delegua/contents/CONTRIBUTING.md","html_url":"https://github.com/DesignLiquido/delegua/blob/principal/CONTRIBUTING.md"},"issue_template":null,"pull_request_template":null,"license":{"key":"mit","name":"MIT License","spdx_id":"MIT","url":"https://api.github.com/licenses/mit","node_id":"MDc6TGljZW5zZTEz","html_url":"https://github.com/DesignLiquido/delegua/blob/principal/LICENSE"},"readme":{"url":"https://api.github.com/repos/DesignLiquido/delegua/contents/README.md","html_url":"https://github.com/DesignLiquido/delegua/blob/principal/README.md"}},"updated_at":"2025-07-16T17:00:12Z","content_reports_enabled":true}